LICENSE
MANIFEST.in
README.md
setup.py
./pyschoof/__init__.py
./pyschoof/__main__.py
./pyschoof/naive_schoof.py
./pyschoof/reduced_computation_schoof.py
./pyschoof/_test/__init__.py
./pyschoof/_test/__main__.py
./pyschoof/_test/algorithm_test.py
./pyschoof/_test/elliptic_curves_group_test.py
./pyschoof/_test/finite_fields_test.py
./pyschoof/_test/fraction_fields_test.py
./pyschoof/_test/polynomial_rings_test.py
./pyschoof/_test/quotient_rings_test.py
./pyschoof/_test/support_test.py
./pyschoof/elliptic_curves/__init__.py
./pyschoof/elliptic_curves/naive.py
./pyschoof/elliptic_curves/division_polynomials/__init__.py
./pyschoof/elliptic_curves/division_polynomials/naive.py
./pyschoof/elliptic_curves/l_torsion_group/__init__.py
./pyschoof/elliptic_curves/l_torsion_group/naive.py
./pyschoof/elliptic_curves/polynomials/__init__.py
./pyschoof/elliptic_curves/polynomials/naive.py
./pyschoof/fields/__init__.py
./pyschoof/fields/finite/__init__.py
./pyschoof/fields/finite/naive.py
./pyschoof/fields/fraction/__init__.py
./pyschoof/fields/fraction/naive.py
./pyschoof/rings/__init__.py
./pyschoof/rings/integers/__init__.py
./pyschoof/rings/integers/naive.py
./pyschoof/rings/polynomials/__init__.py
./pyschoof/rings/polynomials/naive.py
./pyschoof/rings/quotients/__init__.py
./pyschoof/rings/quotients/naive.py
./pyschoof/support/__init__.py
./pyschoof/support/operators.py
./pyschoof/support/primes.py
./pyschoof/support/profiling.py
./pyschoof/support/quotients.py
./pyschoof/support/rings.py
./pyschoof/support/running.py
./pyschoof/support/types.py
pyschoof.egg-info/PKG-INFO
pyschoof.egg-info/SOURCES.txt
pyschoof.egg-info/dependency_links.txt
pyschoof.egg-info/entry_points.txt
pyschoof.egg-info/top_level.txt