Metadata-Version: 1.1
Name: pyschoof
Version: 0.1
Summary: Python implementation of Schoof's algorithm for counting the points on elliptic curves over finite fields
Home-page: UNKNOWN
Author: Peter Dinges, Ryan Kung
Author-email: pdinges@acm.org, ryankung@ieee.org
License:                     GNU GENERAL PUBLIC LICENSE
